simpcli/__init__.py
simpcli-0.0.14.dist-info/DESCRIPTION.rst
simpcli-0.0.14.dist-info/METADATA
simpcli-0.0.14.dist-info/RECORD
simpcli-0.0.14.dist-info/WHEEL
simpcli-0.0.14.dist-info/metadata.json
simpcli-0.0.14.dist-info/top_level.txt
