Metadata-Version: 2.0
Name: simpcli
Version: 0.0.14
Summary: Helper for Python CLI Scripts
Home-page: https://github.com/claudio-walser/python-simplecli
Author: Claudio Walser
Author-email: claudio.walser@srf.ch
License: Apache License
Keywords: cli
Platform: UNKNOWN
Classifier: Development Status :: 4 - Beta
Classifier: Environment :: Plugins
Classifier: Intended Audience :: Developers
Classifier: License :: OSI Approved :: Apache Software License
Classifier: Operating System :: OS Independent
Classifier: Programming Language :: Python :: 3.3
Classifier: Programming Language :: Python :: 3.4
Classifier: Programming Language :: Python :: 3.5
Classifier: Programming Language :: Python :: 3.6
Classifier: Topic :: Utilities
